[
    {
        "ID": "09Alvanoudi-481721",
        "categories": [
            "",
            "3sg",
            "gen",
            "neg",
            "prs",
            "sg"
        ],
        "clength": 121,
        "filename": "216/chapters/09Alvanoudi.tex",
        "imt": "\\textsc{neg} 2\\textsc{sg}.\\textsc{gen} cost\\textsc{.3sg.prs}  very \\hspace{0.3in} much",
        "imtwordsbare": [
            "NEG",
            "2SG.GEN",
            "cost.3sg.prs",
            "very",
            "\\hspace{0.3in}",
            "much"
        ],
        "imtwordshtml": [
            "<span class=\"sc\">neg</span>",
            "2<span class=\"sc\">sg</span>.<span class=\"sc\">gen</span>",
            "cost<span class=\"sc\">.3sg.prs</span>",
            "very",
            "\\hspace{0.3in}",
            "much"
        ],
        "imtwordstex": [
            "\\textsc{neg}",
            "2\\textsc{sg}.\\textsc{gen}",
            "cost\\textsc{.3sg.prs}",
            "very",
            "\\hspace{0.3in}",
            "much"
        ],
        "language": "216/chapters/09Alvanoudi.tex",
        "src": "\\textbf{$\\uparrow$}\\textbf{\\underline{\u00d0e}} \\textbf{su} \\textbf{kost\u00edzi} \\textbf{p\u00e1{[}ra} \\hspace{0.4in} \\textbf{pol\u00ed.{]}}",
        "srcwordsbare": [
            "$\\uparrow$\\underline{\u00d0e}",
            "su",
            "kost\u00edzi",
            "p\u00e1{[ra}",
            "\\hspace{0.4in}",
            "pol\u00ed.{]}"
        ],
        "srcwordshtml": [
            "<span class=\"bf\">$\\uparrow$</span><span class=\"bf\">\\underline{\u00d0e</span>}",
            "<span class=\"bf\">su</span>",
            "<span class=\"bf\">kost\u00edzi</span>",
            "<span class=\"bf\">p\u00e1{[</span>ra}",
            "\\hspace{0.4in}",
            "<span class=\"bf\">pol\u00ed.{]</span>}"
        ],
        "srcwordstex": [
            "\\textbf{$\\uparrow$}\\textbf{\\underline{\u00d0e}}",
            "\\textbf{su}",
            "\\textbf{kost\u00edzi}",
            "\\textbf{p\u00e1{[}ra}",
            "\\hspace{0.4in}",
            "\\textbf{pol\u00ed.{]}}"
        ],
        "trs": "It doesn't cost you very much.'\\\\",
        "wlength": 6
    },
    {
        "ID": "09Alvanoudi-115127",
        "categories": [
            "",
            "3sg",
            "gen",
            "neg",
            "prs",
            "sg"
        ],
        "clength": 79,
        "filename": "216/chapters/09Alvanoudi.tex",
        "imt": "\\hspace{1.7in} \\textsc{neg} 2\\textsc{sg}.\\textsc{gen} cost\\textsc{.3sg.prs}",
        "imtwordsbare": [
            "\\hspace{1.7in}",
            "NEG",
            "2SG.GEN",
            "cost.3sg.prs"
        ],
        "imtwordshtml": [
            "\\hspace{1.7in}",
            "<span class=\"sc\">neg</span>",
            "2<span class=\"sc\">sg</span>.<span class=\"sc\">gen</span>",
            "cost<span class=\"sc\">.3sg.prs</span>"
        ],
        "imtwordstex": [
            "\\hspace{1.7in}",
            "\\textsc{neg}",
            "2\\textsc{sg}.\\textsc{gen}",
            "cost\\textsc{.3sg.prs}"
        ],
        "language": "216/chapters/09Alvanoudi.tex",
        "src": "\\hspace{1.7in}  \\textbf{{[}\\underline{\u00d0e}}  \\textbf{su}\t    \\textbf{ko{]}st\u00edzi}",
        "srcwordsbare": [
            "\\hspace{1.7in}",
            "{[\\underline{\u00d0e}}",
            "su",
            "ko{]st\u00edzi}"
        ],
        "srcwordshtml": [
            "\\hspace{1.7in}",
            "<span class=\"bf\">{[</span>\\underline{\u00d0e}}",
            "<span class=\"bf\">su</span>",
            "<span class=\"bf\">ko{]</span>st\u00edzi}"
        ],
        "srcwordstex": [
            "\\hspace{1.7in}",
            "\\textbf{{[}\\underline{\u00d0e}}",
            "\\textbf{su}",
            "\\textbf{ko{]}st\u00edzi}"
        ],
        "trs": "\\hspace{1.7in}`It doesn't cost you",
        "wlength": 4
    },
    {
        "ID": "09Alvanoudi--90830",
        "categories": [],
        "clength": 31,
        "filename": "216/chapters/09Alvanoudi.tex",
        "imt": "very much",
        "imtwordsbare": [
            "very",
            "much"
        ],
        "imtwordshtml": [
            "very",
            "much"
        ],
        "imtwordstex": [
            "very",
            "much"
        ],
        "language": "216/chapters/09Alvanoudi.tex",
        "src": "\u00b0\\textbf{p\u00e1ra}  \\textbf{pol\u00ed.=}",
        "srcwordsbare": [
            "\u00b0p\u00e1ra",
            "pol\u00ed.="
        ],
        "srcwordshtml": [
            "\u00b0<span class=\"bf\">p\u00e1ra</span>",
            "<span class=\"bf\">pol\u00ed.=</span>"
        ],
        "srcwordstex": [
            "\u00b0\\textbf{p\u00e1ra}",
            "\\textbf{pol\u00ed.=}"
        ],
        "trs": "very much.'\\\\",
        "wlength": 2
    },
    {
        "ID": "09Alvanoudi--65385",
        "categories": [
            "2sg",
            "pfv",
            "sbjv"
        ],
        "clength": 33,
        "filename": "216/chapters/09Alvanoudi.tex",
        "imt": "sit.\\textsc{2sg.pfv} \\textsc{sbjv} \tdo.\\textsc{2sg}",
        "imtwordsbare": [
            "sit.2sg.pfv",
            "SBJV",
            "do.2SG"
        ],
        "imtwordshtml": [
            "sit.<span class=\"sc\">2sg.pfv</span>",
            "<span class=\"sc\">sbjv</span>",
            "do.<span class=\"sc\">2sg</span>"
        ],
        "imtwordstex": [
            "sit.\\textsc{2sg.pfv}",
            "\\textsc{sbjv}",
            "do.\\textsc{2sg}"
        ],
        "language": "216/chapters/09Alvanoudi.tex",
        "src": "k\u00e1\\underline{\\t{ts}}is na\tk\u00e1nis.=",
        "srcwordsbare": [
            "k\u00e1\\underline{\\t{ts}}is",
            "na",
            "k\u00e1nis.="
        ],
        "srcwordshtml": [
            "k\u00e1\\underline{\\t{ts}}is",
            "na",
            "k\u00e1nis.="
        ],
        "srcwordstex": [
            "k\u00e1\\underline{\\t{ts}}is",
            "na",
            "k\u00e1nis.="
        ],
        "trs": "And if you are alone what are you supposed to do.='\\\\",
        "wlength": 3
    },
    {
        "ID": "09Alvanoudi-111642",
        "categories": [
            "2sg",
            "cop",
            "neg",
            "prs"
        ],
        "clength": 75,
        "filename": "216/chapters/09Alvanoudi.tex",
        "imt": "if  \\textsc{cop.2sg.prs} by yourself \t\\textsc{neg} have.\\textsc{2sg.prs}   and",
        "imtwordsbare": [
            "if",
            "cop.2sg.prs",
            "by",
            "yourself",
            "NEG",
            "have.2sg.prs",
            "and"
        ],
        "imtwordshtml": [
            "if",
            "<span class=\"sc\">cop.2sg.prs</span>",
            "by",
            "yourself",
            "<span class=\"sc\">neg</span>",
            "have.<span class=\"sc\">2sg.prs</span>",
            "and"
        ],
        "imtwordstex": [
            "if",
            "\\textsc{cop.2sg.prs}",
            "by",
            "yourself",
            "\\textsc{neg}",
            "have.\\textsc{2sg.prs}",
            "and"
        ],
        "language": "216/chapters/09Alvanoudi.tex",
        "src": "=\\textbf{\u00c1ma} \\textbf{\u00edse}  \\textbf{m\u00f3nos} \\textbf{su}   {[}\u00f0en \u00e9\u00e7is  ce{]}",
        "srcwordsbare": [
            "=\u00c1ma",
            "\u00edse",
            "m\u00f3nos",
            "su",
            "{[}\u00f0en",
            "\u00e9\u00e7is",
            "ce{]}"
        ],
        "srcwordshtml": [
            "=<span class=\"bf\">\u00c1ma</span>",
            "<span class=\"bf\">\u00edse</span>",
            "<span class=\"bf\">m\u00f3nos</span>",
            "<span class=\"bf\">su</span>",
            "{[}\u00f0en",
            "\u00e9\u00e7is",
            "ce{]}"
        ],
        "srcwordstex": [
            "=\\textbf{\u00c1ma}",
            "\\textbf{\u00edse}",
            "\\textbf{m\u00f3nos}",
            "\\textbf{su}",
            "{[}\u00f0en",
            "\u00e9\u00e7is",
            "ce{]}"
        ],
        "trs": "=I think that if you are alone you are not'}\\\\",
        "wlength": 7
    },
    {
        "ID": "09Alvanoudi-114919",
        "categories": [
            "1sg",
            "3pl",
            "conj",
            "cop",
            "pfv",
            "prs",
            "sbjv"
        ],
        "clength": 97,
        "filename": "216/chapters/09Alvanoudi.tex",
        "imt": "no  just   want.\\textsc{1sg.prs}  \\textsc{sbjv} tell.\\textsc{1sg.pfv}  \\textsc{conj}   \\textsc{cop.3pl.prs}",
        "imtwordsbare": [
            "no",
            "just",
            "want.1sg.prs",
            "SBJV",
            "tell.1sg.pfv",
            "CONJ",
            "cop.3pl.prs"
        ],
        "imtwordshtml": [
            "no",
            "just",
            "want.<span class=\"sc\">1sg.prs</span>",
            "<span class=\"sc\">sbjv</span>",
            "tell.<span class=\"sc\">1sg.pfv</span>",
            "<span class=\"sc\">conj</span>",
            "<span class=\"sc\">cop.3pl.prs</span>"
        ],
        "imtwordstex": [
            "no",
            "just",
            "want.\\textsc{1sg.prs}",
            "\\textsc{sbjv}",
            "tell.\\textsc{1sg.pfv}",
            "\\textsc{conj}",
            "\\textsc{cop.3pl.prs}"
        ],
        "language": "216/chapters/09Alvanoudi.tex",
        "modality": "volitive",
        "src": "{[}{[}O\u00e7i. ap\\underline{l\u00e1}{]} \u03b8\u00e9lo             na    po          \t   \u00f3ti     \\textbf{ip\u00e1{]}rxun}",
        "srcwordsbare": [
            "{[}{[}O\u00e7i.",
            "ap\\underline{l\u00e1}{]}",
            "\u03b8\u00e9lo",
            "na",
            "po",
            "\u00f3ti",
            "ip\u00e1{]rxun}"
        ],
        "srcwordshtml": [
            "{[}{[}O\u00e7i.",
            "ap\\underline{l\u00e1}{]}",
            "\u03b8\u00e9lo",
            "na",
            "po",
            "\u00f3ti",
            "<span class=\"bf\">ip\u00e1{]</span>rxun}"
        ],
        "srcwordstex": [
            "{[}{[}O\u00e7i.",
            "ap\\underline{l\u00e1}{]}",
            "\u03b8\u00e9lo",
            "na",
            "po",
            "\u00f3ti",
            "\\textbf{ip\u00e1{]}rxun}"
        ],
        "trs": "No. I just want to say that there are' }\\\\",
        "wlength": 7
    },
    {
        "ID": "09Alvanoudi--78803",
        "categories": [
            "acc",
            "neut",
            "part",
            "pl"
        ],
        "clength": 82,
        "filename": "216/chapters/09Alvanoudi.tex",
        "imt": "certain.\\textsc{neut.acc.pl} standards \\textsc{part} child my",
        "imtwordsbare": [
            "certain.neut.acc.pl",
            "standards",
            "PART",
            "child",
            "my"
        ],
        "imtwordshtml": [
            "certain.<span class=\"sc\">neut.acc.pl</span>",
            "standards",
            "<span class=\"sc\">part</span>",
            "child",
            "my"
        ],
        "imtwordstex": [
            "certain.\\textsc{neut.acc.pl}",
            "standards",
            "\\textsc{part}",
            "child",
            "my"
        ],
        "language": "216/chapters/09Alvanoudi.tex",
        "src": "\\textbf{merik\u00e1}                   \\textbf{\\underline{st\u00e1}dars}  >vre    pe\u00f0\u00ed  mu.<",
        "srcwordsbare": [
            "merik\u00e1",
            "\\underline{st\u00e1dars}",
            ">vre",
            "pe\u00f0\u00ed",
            "mu.<"
        ],
        "srcwordshtml": [
            "<span class=\"bf\">merik\u00e1</span>",
            "<span class=\"bf\">\\underline{st\u00e1</span>dars}",
            ">vre",
            "pe\u00f0\u00ed",
            "mu.<"
        ],
        "srcwordstex": [
            "\\textbf{merik\u00e1}",
            "\\textbf{\\underline{st\u00e1}dars}",
            ">vre",
            "pe\u00f0\u00ed",
            "mu.<"
        ],
        "trs": "certain standards hey you man.'}\\\\",
        "wlength": 5
    },
    {
        "ID": "09Alvanoudi--71250",
        "categories": [
            "3pl",
            "prs"
        ],
        "clength": 65,
        "filename": "216/chapters/09Alvanoudi.tex",
        "imt": ".hh make.\\textsc{3pl.prs} \\hspace{0.05in} group",
        "imtwordsbare": [
            ".hh",
            "make.3pl.prs",
            "\\hspace{0.05in}",
            "group"
        ],
        "imtwordshtml": [
            ".hh",
            "make.<span class=\"sc\">3pl.prs</span>",
            "\\hspace{0.05in}",
            "group"
        ],
        "imtwordstex": [
            ".hh",
            "make.\\textsc{3pl.prs}",
            "\\hspace{0.05in}",
            "group"
        ],
        "language": "216/chapters/09Alvanoudi.tex",
        "src": ".hh \\textbf{k\u00e1nu{[}ne:{]}:} \\hspace{0.05in} \\textbf{{[}:grup},{]}",
        "srcwordsbare": [
            ".hh",
            "k\u00e1nu{[ne:{]}:}",
            "\\hspace{0.05in}",
            "{[:grup},{]}"
        ],
        "srcwordshtml": [
            ".hh",
            "<span class=\"bf\">k\u00e1nu{[</span>ne:{]}:}",
            "\\hspace{0.05in}",
            "<span class=\"bf\">{[</span>:grup},{]}"
        ],
        "srcwordstex": [
            ".hh",
            "\\textbf{k\u00e1nu{[}ne:{]}:}",
            "\\hspace{0.05in}",
            "\\textbf{{[}:grup},{]}"
        ],
        "trs": ".hh they form groups,'}\\\\",
        "wlength": 4
    },
    {
        "ID": "09Alvanoudi-629054",
        "categories": [
            "3pl",
            "3sg",
            "prs"
        ],
        "clength": 61,
        "coordination": "and",
        "filename": "216/chapters/09Alvanoudi.tex",
        "imt": "\\hspace{1.1in}  make.\\textsc{3pl.prs} group and have.\\textsc{3sg.prs}",
        "imtwordsbare": [
            "\\hspace{1.1in}",
            "make.3pl.prs",
            "group",
            "and",
            "have.3sg.prs"
        ],
        "imtwordshtml": [
            "\\hspace{1.1in}",
            "make.<span class=\"sc\">3pl.prs</span>",
            "group",
            "and",
            "have.<span class=\"sc\">3sg.prs</span>"
        ],
        "imtwordstex": [
            "\\hspace{1.1in}",
            "make.\\textsc{3pl.prs}",
            "group",
            "and",
            "have.\\textsc{3sg.prs}"
        ],
        "language": "216/chapters/09Alvanoudi.tex",
        "src": "\\hspace{1.1in} \\textbf{{[}k\u00e1nune{]}} \\textbf{grup},  ci  \u00e9\u00e7i:",
        "srcwordsbare": [
            "\\hspace{1.1in}",
            "{[k\u00e1nune{]}}",
            "grup,",
            "ci",
            "\u00e9\u00e7i:"
        ],
        "srcwordshtml": [
            "\\hspace{1.1in}",
            "<span class=\"bf\">{[</span>k\u00e1nune{]}}",
            "<span class=\"bf\">grup</span>,",
            "ci",
            "\u00e9\u00e7i:"
        ],
        "srcwordstex": [
            "\\hspace{1.1in}",
            "\\textbf{{[}k\u00e1nune{]}}",
            "\\textbf{grup},",
            "ci",
            "\u00e9\u00e7i:"
        ],
        "trs": "\\hspace{1.1in} `they form groups, and it is'}\\\\",
        "wlength": 5
    },
    {
        "ID": "09Alvanoudi--85383",
        "categories": [
            "1pl",
            "neg",
            "pfv",
            "prs",
            "sbjv"
        ],
        "clength": 69,
        "coordination": "and",
        "filename": "216/chapters/09Alvanoudi.tex",
        "imt": "\\textsc{neg} go.\\textsc{1pl.prs} \\textsc{sbjv} cook.\\textsc{1pl.pfv}",
        "imtwordsbare": [
            "NEG",
            "go.1pl.prs",
            "SBJV",
            "cook.1pl.pfv"
        ],
        "imtwordshtml": [
            "<span class=\"sc\">neg</span>",
            "go.<span class=\"sc\">1pl.prs</span>",
            "<span class=\"sc\">sbjv</span>",
            "cook.<span class=\"sc\">1pl.pfv</span>"
        ],
        "imtwordstex": [
            "\\textsc{neg}",
            "go.\\textsc{1pl.prs}",
            "\\textsc{sbjv}",
            "cook.\\textsc{1pl.pfv}"
        ],
        "language": "216/chapters/09Alvanoudi.tex",
        "src": "\\textbf{>\u00d0en} \\textbf{b\u00e1me}      \\textbf{na}   \\textbf{ma\u029dir\u00e9psume?<}",
        "srcwordsbare": [
            ">\u00d0en",
            "b\u00e1me",
            "na",
            "ma\u029dir\u00e9psume?<"
        ],
        "srcwordshtml": [
            "<span class=\"bf\">>\u00d0en</span>",
            "<span class=\"bf\">b\u00e1me</span>",
            "<span class=\"bf\">na</span>",
            "<span class=\"bf\">ma\u029dir\u00e9psume?<</span>"
        ],
        "srcwordstex": [
            "\\textbf{>\u00d0en}",
            "\\textbf{b\u00e1me}",
            "\\textbf{na}",
            "\\textbf{ma\u029dir\u00e9psume?<}"
        ],
        "trs": "Shall we go and cook?'}\\\\",
        "wlength": 4
    },
    {
        "ID": "09Alvanoudi-363068",
        "categories": [
            "2sg",
            "dim",
            "fut",
            "pfv"
        ],
        "clength": 25,
        "filename": "216/chapters/09Alvanoudi.tex",
        "imt": "Eirini.\\textsc{dim} \\textsc{fut} eat.\\textsc{2sg.pfv}",
        "imtwordsbare": [
            "Eirini.DIM",
            "FUT",
            "eat.2sg.pfv"
        ],
        "imtwordshtml": [
            "Eirini.<span class=\"sc\">dim</span>",
            "<span class=\"sc\">fut</span>",
            "eat.<span class=\"sc\">2sg.pfv</span>"
        ],
        "imtwordstex": [
            "Eirini.\\textsc{dim}",
            "\\textsc{fut}",
            "eat.\\textsc{2sg.pfv}"
        ],
        "language": "216/chapters/09Alvanoudi.tex",
        "src": "=Rin\u00e1ci      \u03b8a   fa::s?=",
        "srcwordsbare": [
            "=Rin\u00e1ci",
            "\u03b8a",
            "fa::s?="
        ],
        "srcwordshtml": [
            "=Rin\u00e1ci",
            "\u03b8a",
            "fa::s?="
        ],
        "srcwordstex": [
            "=Rin\u00e1ci",
            "\u03b8a",
            "fa::s?="
        ],
        "trs": "Eirini will you eat?'}\\\\",
        "wlength": 3
    },
    {
        "ID": "09Alvanoudi--86983",
        "categories": [
            "1pl",
            "pfv",
            "sbjv"
        ],
        "clength": 85,
        "coordination": "and",
        "filename": "216/chapters/09Alvanoudi.tex",
        "imt": "so      \\textsc{sbjv} go.\\textsc{1pl} \\textsc{sbjv} cook.\\textsc{1pl.pfv}",
        "imtwordsbare": [
            "so",
            "SBJV",
            "go.1PL",
            "SBJV",
            "cook.1pl.pfv"
        ],
        "imtwordshtml": [
            "so",
            "<span class=\"sc\">sbjv</span>",
            "go.<span class=\"sc\">1pl</span>",
            "<span class=\"sc\">sbjv</span>",
            "cook.<span class=\"sc\">1pl.pfv</span>"
        ],
        "imtwordstex": [
            "so",
            "\\textsc{sbjv}",
            "go.\\textsc{1pl}",
            "\\textsc{sbjv}",
            "cook.\\textsc{1pl.pfv}"
        ],
        "language": "216/chapters/09Alvanoudi.tex",
        "src": "Lip\u00f3n. \\textbf{na} \\textbf{\\underline{p\u00e1}me}      \\textbf{na}   \\textbf{ma\u029dir\u00e9psume?}",
        "srcwordsbare": [
            "Lip\u00f3n.",
            "na",
            "\\underline{p\u00e1me}",
            "na",
            "ma\u029dir\u00e9psume?"
        ],
        "srcwordshtml": [
            "Lip\u00f3n.",
            "<span class=\"bf\">na</span>",
            "<span class=\"bf\">\\underline{p\u00e1</span>me}",
            "<span class=\"bf\">na</span>",
            "<span class=\"bf\">ma\u029dir\u00e9psume?</span>"
        ],
        "srcwordstex": [
            "Lip\u00f3n.",
            "\\textbf{na}",
            "\\textbf{\\underline{p\u00e1}me}",
            "\\textbf{na}",
            "\\textbf{ma\u029dir\u00e9psume?}"
        ],
        "trs": "So. Shall we go and cook?'}\\\\",
        "wlength": 5
    },
    {
        "ID": "09Alvanoudi-467031",
        "categories": [
            "1pl",
            "pfv",
            "sbjv"
        ],
        "clength": 41,
        "filename": "216/chapters/09Alvanoudi.tex",
        "imt": "\\textsc{sbjv} cook.\\textsc{1pl.pfv}",
        "imtwordsbare": [
            "SBJV",
            "cook.1pl.pfv"
        ],
        "imtwordshtml": [
            "<span class=\"sc\">sbjv</span>",
            "cook.<span class=\"sc\">1pl.pfv</span>"
        ],
        "imtwordstex": [
            "\\textsc{sbjv}",
            "cook.\\textsc{1pl.pfv}"
        ],
        "language": "216/chapters/09Alvanoudi.tex",
        "src": "\\textbf{na}   \\textbf{ma\u029dir\u00e9psu{[}me?{]}}",
        "srcwordsbare": [
            "na",
            "ma\u029dir\u00e9psu{[me?{]}}"
        ],
        "srcwordshtml": [
            "<span class=\"bf\">na</span>",
            "<span class=\"bf\">ma\u029dir\u00e9psu{[</span>me?{]}}"
        ],
        "srcwordstex": [
            "\\textbf{na}",
            "\\textbf{ma\u029dir\u00e9psu{[}me?{]}}"
        ],
        "trs": "and cook?'}\\\\",
        "wlength": 2
    },
    {
        "ID": "09Alvanoudi--73715",
        "categories": [
            "2sg",
            "3sg",
            "pass",
            "prs"
        ],
        "clength": 85,
        "filename": "216/chapters/09Alvanoudi.tex",
        "imt": "this announce.\\textsc{3sg.pass.prs} how it learn.\\textsc{2sg.prs}",
        "imtwordsbare": [
            "this",
            "announce.3sg.pass.prs",
            "how",
            "it",
            "learn.2sg.prs"
        ],
        "imtwordshtml": [
            "this",
            "announce.<span class=\"sc\">3sg.pass.prs</span>",
            "how",
            "it",
            "learn.<span class=\"sc\">2sg.prs</span>"
        ],
        "imtwordstex": [
            "this",
            "announce.\\textsc{3sg.pass.prs}",
            "how",
            "it",
            "learn.\\textsc{2sg.prs}"
        ],
        "language": "216/chapters/09Alvanoudi.tex",
        "src": "\\textbf{aft\u03cc}                  \\textbf{\u00f0il\u00f3nete:{[}:?} \\underline{pos} to ma\u03b8\u00e9nis?{]}",
        "srcwordsbare": [
            "aft\u03cc",
            "\u00f0il\u00f3nete:{[:?}",
            "\\underline{pos}",
            "to",
            "ma\u03b8\u00e9nis?{]}"
        ],
        "srcwordshtml": [
            "<span class=\"bf\">aft\u03cc</span>",
            "<span class=\"bf\">\u00f0il\u00f3nete:{[</span>:?}",
            "\\underline{pos}",
            "to",
            "ma\u03b8\u00e9nis?{]}"
        ],
        "srcwordstex": [
            "\\textbf{aft\u03cc}",
            "\\textbf{\u00f0il\u00f3nete:{[}:?}",
            "\\underline{pos}",
            "to",
            "ma\u03b8\u00e9nis?{]}"
        ],
        "trs": "Is this announced? How do you find out about it?'}\\\\",
        "wlength": 5
    },
    {
        "ID": "09Alvanoudi--13490",
        "categories": [
            "2sg",
            "prs"
        ],
        "clength": 96,
        "filename": "216/chapters/09Alvanoudi.tex",
        "imt": "\\hspace{0.8in} it learn.\\textsc{2sg.prs} \\hspace{0.55in} usually",
        "imtwordsbare": [
            "\\hspace{0.8in}",
            "it",
            "learn.2sg.prs",
            "\\hspace{0.55in}",
            "usually"
        ],
        "imtwordshtml": [
            "\\hspace{0.8in}",
            "it",
            "learn.<span class=\"sc\">2sg.prs</span>",
            "\\hspace{0.55in}",
            "usually"
        ],
        "imtwordstex": [
            "\\hspace{0.8in}",
            "it",
            "learn.\\textsc{2sg.prs}",
            "\\hspace{0.55in}",
            "usually"
        ],
        "language": "216/chapters/09Alvanoudi.tex",
        "src": "\\hspace{0.8in} \\textbf{{[}To} \\textbf{ma\\underline{\u03b8\u00e9}nis} \\hspace{0.55in} \\textbf{\u00b0sin\u00ed{]}\u03b8os}.",
        "srcwordsbare": [
            "\\hspace{0.8in}",
            "{[To}",
            "ma\\underline{\u03b8\u00e9nis}",
            "\\hspace{0.55in}",
            "\u00b0sin\u00ed{]\u03b8os}."
        ],
        "srcwordshtml": [
            "\\hspace{0.8in}",
            "<span class=\"bf\">{[</span>To}",
            "<span class=\"bf\">ma\\underline{\u03b8\u00e9</span>nis}",
            "\\hspace{0.55in}",
            "<span class=\"bf\">\u00b0sin\u00ed{]</span>\u03b8os}."
        ],
        "srcwordstex": [
            "\\hspace{0.8in}",
            "\\textbf{{[}To}",
            "\\textbf{ma\\underline{\u03b8\u00e9}nis}",
            "\\hspace{0.55in}",
            "\\textbf{\u00b0sin\u00ed{]}\u03b8os}."
        ],
        "trs": "\\hspace{0.8in}`Usually you find out about it'}\\\\",
        "wlength": 5
    },
    {
        "ID": "09Alvanoudi-863411",
        "categories": [
            "2sg",
            "prs"
        ],
        "clength": 49,
        "filename": "216/chapters/09Alvanoudi.tex",
        "imt": "usually it learn.\\textsc{2sg.prs}",
        "imtwordsbare": [
            "usually",
            "it",
            "learn.2sg.prs"
        ],
        "imtwordshtml": [
            "usually",
            "it",
            "learn.<span class=\"sc\">2sg.prs</span>"
        ],
        "imtwordstex": [
            "usually",
            "it",
            "learn.\\textsc{2sg.prs}"
        ],
        "language": "216/chapters/09Alvanoudi.tex",
        "src": "\\textbf{>sin\u00ed\u03b8os<} \\textbf{to} \\textbf{ma\u03b8\u00e9nis}.\u00b0",
        "srcwordsbare": [
            ">sin\u00ed\u03b8os<",
            "to",
            "ma\u03b8\u00e9nis.\u00b0"
        ],
        "srcwordshtml": [
            "<span class=\"bf\">>sin\u00ed\u03b8os<</span>",
            "<span class=\"bf\">to</span>",
            "<span class=\"bf\">ma\u03b8\u00e9nis</span>.\u00b0"
        ],
        "srcwordstex": [
            "\\textbf{>sin\u00ed\u03b8os<}",
            "\\textbf{to}",
            "\\textbf{ma\u03b8\u00e9nis}.\u00b0"
        ],
        "trs": "Usually you find out about it.'}\\\\",
        "wlength": 3
    },
    {
        "ID": "09Alvanoudi-858662",
        "categories": [
            "2pl",
            "prs"
        ],
        "clength": 59,
        "filename": "216/chapters/09Alvanoudi.tex",
        "imt": "Mara     when leave.\\textsc{2pl.prs}",
        "imtwordsbare": [
            "Mara",
            "when",
            "leave.2pl.prs"
        ],
        "imtwordshtml": [
            "Mara",
            "when",
            "leave.<span class=\"sc\">2pl.prs</span>"
        ],
        "imtwordstex": [
            "Mara",
            "when",
            "leave.\\textsc{2pl.prs}"
        ],
        "language": "216/chapters/09Alvanoudi.tex",
        "src": "\\textbf{=M\u00e1ra,} \\textbf{p\u00f3te} \\textbf{{[}f\u00e9v\u029dete}(.....){]}",
        "srcwordsbare": [
            "=M\u00e1ra,",
            "p\u00f3te",
            "{[f\u00e9v\u029dete}(.....){]}"
        ],
        "srcwordshtml": [
            "<span class=\"bf\">=M\u00e1ra,</span>",
            "<span class=\"bf\">p\u00f3te</span>",
            "<span class=\"bf\">{[</span>f\u00e9v\u029dete}(.....){]}"
        ],
        "srcwordstex": [
            "\\textbf{=M\u00e1ra,}",
            "\\textbf{p\u00f3te}",
            "\\textbf{{[}f\u00e9v\u029dete}(.....){]}"
        ],
        "trs": "Mara, when are you leaving (...)'}\\\\",
        "wlength": 3
    },
    {
        "ID": "09Alvanoudi-735139",
        "categories": [
            "2pl",
            "fut",
            "pfv"
        ],
        "clength": 59,
        "filename": "216/chapters/09Alvanoudi.tex",
        "imt": "when \\textsc{fut} leave.\\textsc{2pl.pfv}",
        "imtwordsbare": [
            "when",
            "FUT",
            "leave.2pl.pfv"
        ],
        "imtwordshtml": [
            "when",
            "<span class=\"sc\">fut</span>",
            "leave.<span class=\"sc\">2pl.pfv</span>"
        ],
        "imtwordstex": [
            "when",
            "\\textsc{fut}",
            "leave.\\textsc{2pl.pfv}"
        ],
        "language": "216/chapters/09Alvanoudi.tex",
        "src": "\\textbf{=}\\textbf{>P\u00f3{[}te} \\textbf{\u03b8a} \\textbf{fi\u029dete}<{]}",
        "srcwordsbare": [
            "=>P\u00f3{[te}",
            "\u03b8a",
            "fi\u029dete<{]}"
        ],
        "srcwordshtml": [
            "<span class=\"bf\">=</span><span class=\"bf\">>P\u00f3{[</span>te}",
            "<span class=\"bf\">\u03b8a</span>",
            "<span class=\"bf\">fi\u029dete</span><{]}"
        ],
        "srcwordstex": [
            "\\textbf{=}\\textbf{>P\u00f3{[}te}",
            "\\textbf{\u03b8a}",
            "\\textbf{fi\u029dete}<{]}"
        ],
        "trs": "When are you leaving?'}\\\\",
        "wlength": 3
    },
    {
        "ID": "09Alvanoudi-683158",
        "categories": [
            "2pl",
            "fut",
            "nom",
            "pfv"
        ],
        "clength": 86,
        "filename": "216/chapters/09Alvanoudi.tex",
        "imt": "when \\textsc{fut} leave.\\textsc{2pl.pfv} \\textsc{2pl.nom}",
        "imtwordsbare": [
            "when",
            "FUT",
            "leave.2pl.pfv",
            "2pl.nom"
        ],
        "imtwordshtml": [
            "when",
            "<span class=\"sc\">fut</span>",
            "leave.<span class=\"sc\">2pl.pfv</span>",
            "<span class=\"sc\">2pl.nom</span>"
        ],
        "imtwordstex": [
            "when",
            "\\textsc{fut}",
            "leave.\\textsc{2pl.pfv}",
            "\\textsc{2pl.nom}"
        ],
        "language": "216/chapters/09Alvanoudi.tex",
        "src": "\\textbf{=}\\textbf{>\\underline{P\u00f3}te} \\textbf{\u03b8a} \\textbf{fi\u029dete} \\textbf{es{[}\u00eds?<{]}}",
        "srcwordsbare": [
            "=>\\underline{P\u00f3te}",
            "\u03b8a",
            "fi\u029dete",
            "es{[\u00eds?<{]}}"
        ],
        "srcwordshtml": [
            "<span class=\"bf\">=</span><span class=\"bf\">>\\underline{P\u00f3</span>te}",
            "<span class=\"bf\">\u03b8a</span>",
            "<span class=\"bf\">fi\u029dete</span>",
            "<span class=\"bf\">es{[</span>\u00eds?<{]}}"
        ],
        "srcwordstex": [
            "\\textbf{=}\\textbf{>\\underline{P\u00f3}te}",
            "\\textbf{\u03b8a}",
            "\\textbf{fi\u029dete}",
            "\\textbf{es{[}\u00eds?<{]}}"
        ],
        "trs": "When are you leaving?'}\\\\",
        "wlength": 4
    },
    {
        "ID": "09Alvanoudi--87191",
        "categories": [
            "2pl",
            "fut",
            "nom",
            "pfv"
        ],
        "clength": 88,
        "filename": "216/chapters/09Alvanoudi.tex",
        "imt": "when \\textsc{fut} leave.\\textsc{2pl.pfv} \\textsc{2pl.nom}",
        "imtwordsbare": [
            "when",
            "FUT",
            "leave.2pl.pfv",
            "2pl.nom"
        ],
        "imtwordshtml": [
            "when",
            "<span class=\"sc\">fut</span>",
            "leave.<span class=\"sc\">2pl.pfv</span>",
            "<span class=\"sc\">2pl.nom</span>"
        ],
        "imtwordstex": [
            "when",
            "\\textsc{fut}",
            "leave.\\textsc{2pl.pfv}",
            "\\textsc{2pl.nom}"
        ],
        "language": "216/chapters/09Alvanoudi.tex",
        "src": "\\textbf{{[}>\\underline{P\u00f3}te} \\textbf{\u03b8a}{]} \\textbf{fi\u029dete} \\textbf{e\\underline{s\u00eds}.}<",
        "srcwordsbare": [
            "{[>\\underline{P\u00f3}te}",
            "\u03b8a{]}",
            "fi\u029dete",
            "e\\underline{s\u00eds.}<"
        ],
        "srcwordshtml": [
            "<span class=\"bf\">{[</span>>\\underline{P\u00f3}te}",
            "<span class=\"bf\">\u03b8a</span>{]}",
            "<span class=\"bf\">fi\u029dete</span>",
            "<span class=\"bf\">e\\underline{s\u00eds</span>.}<"
        ],
        "srcwordstex": [
            "\\textbf{{[}>\\underline{P\u00f3}te}",
            "\\textbf{\u03b8a}{]}",
            "\\textbf{fi\u029dete}",
            "\\textbf{e\\underline{s\u00eds}.}<"
        ],
        "trs": "When are you leaving?'}\\\\",
        "wlength": 4
    },
    {
        "ID": "09Alvanoudi-726710",
        "categories": [
            "2sg",
            "3sg",
            "cop",
            "nom",
            "prs",
            "sbjv"
        ],
        "clength": 59,
        "filename": "216/chapters/09Alvanoudi.tex",
        "imt": "\\textsc{2sg.nom} \\textsc{sbjv} \\textsc{cop.2sg.prs} like.that  live.\\textsc{3sg.prs} or",
        "imtwordsbare": [
            "2sg.nom",
            "SBJV",
            "cop.2sg.prs",
            "like.that",
            "live.3sg.prs",
            "or"
        ],
        "imtwordshtml": [
            "<span class=\"sc\">2sg.nom</span>",
            "<span class=\"sc\">sbjv</span>",
            "<span class=\"sc\">cop.2sg.prs</span>",
            "like.that",
            "live.<span class=\"sc\">3sg.prs</span>",
            "or"
        ],
        "imtwordstex": [
            "\\textsc{2sg.nom}",
            "\\textsc{sbjv}",
            "\\textsc{cop.2sg.prs}",
            "like.that",
            "live.\\textsc{3sg.prs}",
            "or"
        ],
        "language": "216/chapters/09Alvanoudi.tex",
        "src": "es\u00ed  na  se  \\underline{\u00e9\\t{ts}}i.  \\textbf{zi}  \\textbf{i}",
        "srcwordsbare": [
            "es\u00ed",
            "na",
            "se",
            "\\underline{\u00e9\\t{ts}}i.",
            "zi",
            "i"
        ],
        "srcwordshtml": [
            "es\u00ed",
            "na",
            "se",
            "\\underline{\u00e9\\t{ts}}i.",
            "<span class=\"bf\">zi</span>",
            "<span class=\"bf\">i</span>"
        ],
        "srcwordstex": [
            "es\u00ed",
            "na",
            "se",
            "\\underline{\u00e9\\t{ts}}i.",
            "\\textbf{zi}",
            "\\textbf{i}"
        ],
        "trs": "you are wondering. Is he alive or'}\\\\",
        "wlength": 6
    },
    {
        "ID": "09Alvanoudi--85562",
        "categories": [
            "3sg",
            "pst"
        ],
        "clength": 16,
        "filename": "216/chapters/09Alvanoudi.tex",
        "imt": "die.\\textsc{3sg.pst}",
        "imtwordsbare": [
            "die.3sg.pst"
        ],
        "imtwordshtml": [
            "die.<span class=\"sc\">3sg.pst</span>"
        ],
        "imtwordstex": [
            "die.\\textsc{3sg.pst}"
        ],
        "language": "216/chapters/09Alvanoudi.tex",
        "src": "\\textbf{p\u00e9\u03b8ane?}",
        "srcwordsbare": [
            "p\u00e9\u03b8ane?"
        ],
        "srcwordshtml": [
            "<span class=\"bf\">p\u00e9\u03b8ane?</span>"
        ],
        "srcwordstex": [
            "\\textbf{p\u00e9\u03b8ane?}"
        ],
        "trs": "dead?'}\\\\",
        "wlength": 1
    },
    {
        "ID": "09Alvanoudi--31981",
        "categories": [
            "3sg",
            "prs",
            "pst"
        ],
        "clength": 87,
        "coordination": "or",
        "filename": "216/chapters/09Alvanoudi.tex",
        "imt": "live.\\textsc{3sg.prs} or die.\\textsc{3sg.pst} live.\\textsc{3sg.prs} or die.\\textsc{3sg.pst}",
        "imtwordsbare": [
            "live.3sg.prs",
            "or",
            "die.3sg.pst",
            "live.3sg.prs",
            "or",
            "die.3sg.pst"
        ],
        "imtwordshtml": [
            "live.<span class=\"sc\">3sg.prs</span>",
            "or",
            "die.<span class=\"sc\">3sg.pst</span>",
            "live.<span class=\"sc\">3sg.prs</span>",
            "or",
            "die.<span class=\"sc\">3sg.pst</span>"
        ],
        "imtwordstex": [
            "live.\\textsc{3sg.prs}",
            "or",
            "die.\\textsc{3sg.pst}",
            "live.\\textsc{3sg.prs}",
            "or",
            "die.\\textsc{3sg.pst}"
        ],
        "language": "216/chapters/09Alvanoudi.tex",
        "src": "\\textbf{zi}  \\textbf{i} \\textbf{p\u00e9\u03b8ane,} \\textbf{{[}zi}  \\textbf{i} \\textbf{p\u00e9{]}\u03b8ane,}",
        "srcwordsbare": [
            "zi",
            "i",
            "p\u00e9\u03b8ane,",
            "{[zi}",
            "i",
            "p\u00e9{]\u03b8ane,}"
        ],
        "srcwordshtml": [
            "<span class=\"bf\">zi</span>",
            "<span class=\"bf\">i</span>",
            "<span class=\"bf\">p\u00e9\u03b8ane,</span>",
            "<span class=\"bf\">{[</span>zi}",
            "<span class=\"bf\">i</span>",
            "<span class=\"bf\">p\u00e9{]</span>\u03b8ane,}"
        ],
        "srcwordstex": [
            "\\textbf{zi}",
            "\\textbf{i}",
            "\\textbf{p\u00e9\u03b8ane,}",
            "\\textbf{{[}zi}",
            "\\textbf{i}",
            "\\textbf{p\u00e9{]}\u03b8ane,}"
        ],
        "trs": "he alive or dead, he alive or dead'}\\\\",
        "wlength": 6
    },
    {
        "ID": "09Alvanoudi--25234",
        "categories": [],
        "clength": 7,
        "filename": "216/chapters/09Alvanoudi.tex",
        "imt": "hh and",
        "imtwordsbare": [
            "hh",
            "and"
        ],
        "imtwordshtml": [
            "hh",
            "and"
        ],
        "imtwordstex": [
            "hh",
            "and"
        ],
        "language": "216/chapters/09Alvanoudi.tex",
        "src": ".hh ce:",
        "srcwordsbare": [
            ".hh",
            "ce:"
        ],
        "srcwordshtml": [
            ".hh",
            "ce:"
        ],
        "srcwordstex": [
            ".hh",
            "ce:"
        ],
        "trs": ".hh and'}\\\\",
        "wlength": 2
    },
    {
        "ID": "09Alvanoudi-737010",
        "categories": [
            "3sg",
            "cop",
            "neg",
            "prs"
        ],
        "clength": 86,
        "coordination": "and",
        "filename": "216/chapters/09Alvanoudi.tex",
        "imt": "and \\textsc{neg} and \\textsc{cop.3sg.prs} so ridiculous",
        "imtwordsbare": [
            "and",
            "NEG",
            "and",
            "cop.3sg.prs",
            "so",
            "ridiculous"
        ],
        "imtwordshtml": [
            "and",
            "<span class=\"sc\">neg</span>",
            "and",
            "<span class=\"sc\">cop.3sg.prs</span>",
            "so",
            "ridiculous"
        ],
        "imtwordstex": [
            "and",
            "\\textsc{neg}",
            "and",
            "\\textsc{cop.3sg.prs}",
            "so",
            "ridiculous"
        ],
        "language": "216/chapters/09Alvanoudi.tex",
        "src": "{[}Ce   \u00f0e-  ci   \\textbf{\u00edne}             \\textbf{t\\underline{\u03cc}{]}so} \\textbf{\u029del\u00edo}",
        "srcwordsbare": [
            "{[}Ce",
            "\u00f0e-",
            "ci",
            "\u00edne",
            "t\\underline{\u03cc{]}so}",
            "\u029del\u00edo"
        ],
        "srcwordshtml": [
            "{[}Ce",
            "\u00f0e-",
            "ci",
            "<span class=\"bf\">\u00edne</span>",
            "<span class=\"bf\">t\\underline{\u03cc</span>{]}so}",
            "<span class=\"bf\">\u029del\u00edo</span>"
        ],
        "srcwordstex": [
            "{[}Ce",
            "\u00f0e-",
            "ci",
            "\\textbf{\u00edne}",
            "\\textbf{t\\underline{\u03cc}{]}so}",
            "\\textbf{\u029del\u00edo}"
        ],
        "trs": "And not- and is it such a ridiculous'}\\\\",
        "wlength": 6
    },
    {
        "ID": "09Alvanoudi--20973",
        "categories": [
            "(neut)",
            "3sg",
            "cop",
            "nom",
            "prs",
            "sg"
        ],
        "clength": 82,
        "filename": "216/chapters/09Alvanoudi.tex",
        "imt": "yes \\textsc{cop.3sg.prs}  ridiculous argument\\textsc{(neut).nom.sg}",
        "imtwordsbare": [
            "yes",
            "cop.3sg.prs",
            "ridiculous",
            "argument(neut).nom.sg"
        ],
        "imtwordshtml": [
            "yes",
            "<span class=\"sc\">cop.3sg.prs</span>",
            "ridiculous",
            "argument<span class=\"sc\">(neut).nom.sg</span>"
        ],
        "imtwordstex": [
            "yes",
            "\\textsc{cop.3sg.prs}",
            "ridiculous",
            "argument\\textsc{(neut).nom.sg}"
        ],
        "language": "216/chapters/09Alvanoudi.tex",
        "src": "{[}Ne   \\textbf{\u00edne}             \\textbf{\u029de\\underline{l\u00ed}o} \\textbf{epi{]}\u00e7\u00edrima?}",
        "srcwordsbare": [
            "{[}Ne",
            "\u00edne",
            "\u029de\\underline{l\u00edo}",
            "epi{]\u00e7\u00edrima?}"
        ],
        "srcwordshtml": [
            "{[}Ne",
            "<span class=\"bf\">\u00edne</span>",
            "<span class=\"bf\">\u029de\\underline{l\u00ed</span>o}",
            "<span class=\"bf\">epi{]</span>\u00e7\u00edrima?}"
        ],
        "srcwordstex": [
            "{[}Ne",
            "\\textbf{\u00edne}",
            "\\textbf{\u029de\\underline{l\u00ed}o}",
            "\\textbf{epi{]}\u00e7\u00edrima?}"
        ],
        "trs": "Yes it is a ridiculous argument,'}\\\\",
        "wlength": 4
    },
    {
        "ID": "09Alvanoudi-737364",
        "categories": [
            "3sg",
            "cop",
            "pst"
        ],
        "clength": 5,
        "filename": "216/chapters/09Alvanoudi.tex",
        "imt": "\\textsc{cop.3sg.pst}",
        "imtwordsbare": [
            "cop.3sg.pst"
        ],
        "imtwordshtml": [
            "<span class=\"sc\">cop.3sg.pst</span>"
        ],
        "imtwordstex": [
            "\\textsc{cop.3sg.pst}"
        ],
        "language": "216/chapters/09Alvanoudi.tex",
        "src": "Itan-",
        "srcwordsbare": [
            "Itan-"
        ],
        "srcwordshtml": [
            "Itan-"
        ],
        "srcwordstex": [
            "Itan-"
        ],
        "trs": "Was-'}\\\\",
        "wlength": 1
    },
    {
        "ID": "09Alvanoudi--49968",
        "categories": [
            "def",
            "neut",
            "nom",
            "sg"
        ],
        "clength": 70,
        "filename": "216/chapters/09Alvanoudi.tex",
        "imt": "\\textsc{def.neut.nom.sg} Hatzikosta",
        "imtwordsbare": [
            "def.neut.nom.sg",
            "Hatzikosta"
        ],
        "imtwordshtml": [
            "<span class=\"sc\">def.neut.nom.sg</span>",
            "Hatzikosta"
        ],
        "imtwordstex": [
            "\\textsc{def.neut.nom.sg}",
            "Hatzikosta"
        ],
        "language": "216/chapters/09Alvanoudi.tex",
        "src": "\\textbf{to}                       \\textbf{Xa\\underline{\\t{dz}i}k\u00f3sta.}",
        "srcwordsbare": [
            "to",
            "Xa\\underline{\\t{dzi}k\u00f3sta.}"
        ],
        "srcwordshtml": [
            "<span class=\"bf\">to</span>",
            "<span class=\"bf\">Xa\\underline{\\t{dz</span>i}k\u00f3sta.}"
        ],
        "srcwordstex": [
            "\\textbf{to}",
            "\\textbf{Xa\\underline{\\t{dz}i}k\u00f3sta.}"
        ],
        "trs": "The Hatzikosta hospital was open.'}\\\\",
        "wlength": 2
    },
    {
        "ID": "09Alvanoudi--47980",
        "categories": [
            "3sg",
            "cop",
            "def",
            "f",
            "nom",
            "prs",
            "sg"
        ],
        "clength": 74,
        "filename": "216/chapters/09Alvanoudi.tex",
        "imt": "just     \\textsc{cop.3sg.prs}  weird.\\textsc{f.nom.sg} \\textsc{def.f.nom.sg}",
        "imtwordsbare": [
            "just",
            "cop.3sg.prs",
            "weird.f.nom.sg",
            "def.f.nom.sg"
        ],
        "imtwordshtml": [
            "just",
            "<span class=\"sc\">cop.3sg.prs</span>",
            "weird.<span class=\"sc\">f.nom.sg</span>",
            "<span class=\"sc\">def.f.nom.sg</span>"
        ],
        "imtwordstex": [
            "just",
            "\\textsc{cop.3sg.prs}",
            "weird.\\textsc{f.nom.sg}",
            "\\textsc{def.f.nom.sg}"
        ],
        "language": "216/chapters/09Alvanoudi.tex",
        "src": "=\u0391pl\u00f3s \\textbf{\u00edne}              \\textbf{per\u00eder\u029di}              \\textbf{i}",
        "srcwordsbare": [
            "=\u0391pl\u00f3s",
            "\u00edne",
            "per\u00eder\u029di",
            "i"
        ],
        "srcwordshtml": [
            "=\u0391pl\u00f3s",
            "<span class=\"bf\">\u00edne</span>",
            "<span class=\"bf\">per\u00eder\u029di</span>",
            "<span class=\"bf\">i</span>"
        ],
        "srcwordstex": [
            "=\u0391pl\u00f3s",
            "\\textbf{\u00edne}",
            "\\textbf{per\u00eder\u029di}",
            "\\textbf{i}"
        ],
        "trs": "It\u2019s just a weird'}\\\\",
        "wlength": 4
    },
    {
        "ID": "09Alvanoudi--14677",
        "categories": [
            "3sg",
            "cop",
            "f",
            "nom",
            "prs",
            "sg"
        ],
        "clength": 61,
        "filename": "216/chapters/09Alvanoudi.tex",
        "imt": "\\textsc{cop.3sg.prs}  weird.\\textsc{f.nom.sg}",
        "imtwordsbare": [
            "cop.3sg.prs",
            "weird.f.nom.sg"
        ],
        "imtwordshtml": [
            "<span class=\"sc\">cop.3sg.prs</span>",
            "weird.<span class=\"sc\">f.nom.sg</span>"
        ],
        "imtwordstex": [
            "\\textsc{cop.3sg.prs}",
            "weird.\\textsc{f.nom.sg}"
        ],
        "language": "216/chapters/09Alvanoudi.tex",
        "src": "\\textbf{{[}Ine}              \\textbf{pe\\underline{r\u00ed}{]}er\u029di}",
        "srcwordsbare": [
            "{[Ine}",
            "pe\\underline{r\u00ed{]}er\u029di}"
        ],
        "srcwordshtml": [
            "<span class=\"bf\">{[</span>Ine}",
            "<span class=\"bf\">pe\\underline{r\u00ed</span>{]}er\u029di}"
        ],
        "srcwordstex": [
            "\\textbf{{[}Ine}",
            "\\textbf{pe\\underline{r\u00ed}{]}er\u029di}"
        ],
        "trs": "}\\\\",
        "wlength": 2
    },
    {
        "ID": "09Alvanoudi--14234",
        "categories": [
            "(f)",
            "def",
            "f",
            "nom",
            "sg"
        ],
        "clength": 51,
        "filename": "216/chapters/09Alvanoudi.tex",
        "imt": "\\textsc{def.f.nom.sg} area\\textsc{(f).nom.sg}  this",
        "imtwordsbare": [
            "def.f.nom.sg",
            "area(f).nom.sg",
            "this"
        ],
        "imtwordshtml": [
            "<span class=\"sc\">def.f.nom.sg</span>",
            "area<span class=\"sc\">(f).nom.sg</span>",
            "this"
        ],
        "imtwordstex": [
            "\\textsc{def.f.nom.sg}",
            "area\\textsc{(f).nom.sg}",
            "this"
        ],
        "language": "216/chapters/09Alvanoudi.tex",
        "src": "\\textbf{i}                \\textbf{perio\u00e7\u00ed.}  \u029daft\u00f3.",
        "srcwordsbare": [
            "i",
            "perio\u00e7\u00ed.",
            "\u029daft\u00f3."
        ],
        "srcwordshtml": [
            "<span class=\"bf\">i</span>",
            "<span class=\"bf\">perio\u00e7\u00ed.</span>",
            "\u029daft\u00f3."
        ],
        "srcwordstex": [
            "\\textbf{i}",
            "\\textbf{perio\u00e7\u00ed.}",
            "\u029daft\u00f3."
        ],
        "trs": "It\u2019s a weird neighborhood. That\u2019s why.'}\\\\",
        "wlength": 3
    },
    {
        "ID": "09Alvanoudi-727524",
        "categories": [
            "3sg",
            "prs"
        ],
        "clength": 114,
        "filename": "216/chapters/09Alvanoudi.tex",
        "imt": "them them  regulate.\\textsc{3sg.prs}  now   very well",
        "imtwordsbare": [
            "them",
            "them",
            "regulate.3sg.prs",
            "now",
            "very",
            "well"
        ],
        "imtwordshtml": [
            "them",
            "them",
            "regulate.<span class=\"sc\">3sg.prs</span>",
            "now",
            "very",
            "well"
        ],
        "imtwordstex": [
            "them",
            "them",
            "regulate.\\textsc{3sg.prs}",
            "now",
            "very",
            "well"
        ],
        "language": "216/chapters/09Alvanoudi.tex",
        "src": "\\textbf{ta:}    \\textbf{ta}     \\textbf{ri\u03b8\u00edmzi}              \\textbf{$\\uparrow$t\u00f3ra}  \\textbf{m\u0272a} \\textbf{xar\u00e1}.",
        "srcwordsbare": [
            "ta:",
            "ta",
            "ri\u03b8\u00edmzi",
            "$\\uparrow$t\u00f3ra",
            "m\u0272a",
            "xar\u00e1."
        ],
        "srcwordshtml": [
            "<span class=\"bf\">ta:</span>",
            "<span class=\"bf\">ta</span>",
            "<span class=\"bf\">ri\u03b8\u00edmzi</span>",
            "<span class=\"bf\">$\\uparrow$t\u00f3ra</span>",
            "<span class=\"bf\">m\u0272a</span>",
            "<span class=\"bf\">xar\u00e1</span>."
        ],
        "srcwordstex": [
            "\\textbf{ta:}",
            "\\textbf{ta}",
            "\\textbf{ri\u03b8\u00edmzi}",
            "\\textbf{$\\uparrow$t\u00f3ra}",
            "\\textbf{m\u0272a}",
            "\\textbf{xar\u00e1}."
        ],
        "trs": "he keeps things- things in moderation very well.'}\\\\",
        "wlength": 6
    },
    {
        "ID": "09Alvanoudi-318294",
        "categories": [
            "3sg",
            "neg",
            "prs"
        ],
        "clength": 63,
        "filename": "216/chapters/09Alvanoudi.tex",
        "imt": "\\textsc{neg} them regulate.\\textsc{3sg.prs}",
        "imtwordsbare": [
            "NEG",
            "them",
            "regulate.3sg.prs"
        ],
        "imtwordshtml": [
            "<span class=\"sc\">neg</span>",
            "them",
            "regulate.<span class=\"sc\">3sg.prs</span>"
        ],
        "imtwordstex": [
            "\\textsc{neg}",
            "them",
            "regulate.\\textsc{3sg.prs}"
        ],
        "language": "216/chapters/09Alvanoudi.tex",
        "src": "\u00b0\\textbf{(\\underline{\u00f0e}}   \\textbf{ta}      \\textbf{ri\u03b8m\u00edzi.)}",
        "srcwordsbare": [
            "\u00b0(\\underline{\u00f0e}",
            "ta",
            "ri\u03b8m\u00edzi.)"
        ],
        "srcwordshtml": [
            "\u00b0<span class=\"bf\">(\\underline{\u00f0e</span>}",
            "<span class=\"bf\">ta</span>",
            "<span class=\"bf\">ri\u03b8m\u00edzi.)</span>"
        ],
        "srcwordstex": [
            "\u00b0\\textbf{(\\underline{\u00f0e}}",
            "\\textbf{ta}",
            "\\textbf{ri\u03b8m\u00edzi.)}"
        ],
        "trs": "He doesn\u2019t keep things in moderation.'}\\\\",
        "wlength": 3
    },
    {
        "ID": "09Alvanoudi--56621",
        "categories": [
            "1pl",
            "neg",
            "pst"
        ],
        "clength": 115,
        "filename": "216/chapters/09Alvanoudi.tex",
        "imt": "no    why \\textsc{neg}  it   do.\\textsc{1pl.pst} \\textsc{1pl}     \\textsc{1pl}    it  do.\\textsc{1pl.pst}",
        "imtwordsbare": [
            "no",
            "why",
            "NEG",
            "it",
            "do.1pl.pst",
            "1PL",
            "1PL",
            "it",
            "do.1pl.pst"
        ],
        "imtwordshtml": [
            "no",
            "why",
            "<span class=\"sc\">neg</span>",
            "it",
            "do.<span class=\"sc\">1pl.pst</span>",
            "<span class=\"sc\">1pl</span>",
            "<span class=\"sc\">1pl</span>",
            "it",
            "do.<span class=\"sc\">1pl.pst</span>"
        ],
        "imtwordstex": [
            "no",
            "why",
            "\\textsc{neg}",
            "it",
            "do.\\textsc{1pl.pst}",
            "\\textsc{1pl}",
            "\\textsc{1pl}",
            "it",
            "do.\\textsc{1pl.pst}"
        ],
        "language": "216/chapters/09Alvanoudi.tex",
        "src": "\\underline{O}\u00e7i. \u029da\\underline{ti}   \u00f0en  do k\u00e1name    em\u00eds. =\\textbf{em\u00eds} \\textbf{to} \\textbf{\\underline{k\u00e1}name}.",
        "srcwordsbare": [
            "\\underline{O}\u00e7i.",
            "\u029da\\underline{ti}",
            "\u00f0en",
            "do",
            "k\u00e1name",
            "em\u00eds.",
            "=em\u00eds",
            "to",
            "\\underline{k\u00e1name}."
        ],
        "srcwordshtml": [
            "\\underline{O}\u00e7i.",
            "\u029da\\underline{ti}",
            "\u00f0en",
            "do",
            "k\u00e1name",
            "em\u00eds.",
            "=<span class=\"bf\">em\u00eds</span>",
            "<span class=\"bf\">to</span>",
            "<span class=\"bf\">\\underline{k\u00e1</span>name}."
        ],
        "srcwordstex": [
            "\\underline{O}\u00e7i.",
            "\u029da\\underline{ti}",
            "\u00f0en",
            "do",
            "k\u00e1name",
            "em\u00eds.",
            "=\\textbf{em\u00eds}",
            "\\textbf{to}",
            "\\textbf{\\underline{k\u00e1}name}."
        ],
        "trs": "No. Why didn\u2019t we do the same? We did it.'}\\\\",
        "wlength": 9
    },
    {
        "ID": "09Alvanoudi-664511",
        "categories": [
            "1pl",
            "pst"
        ],
        "clength": 75,
        "filename": "216/chapters/09Alvanoudi.tex",
        "imt": "it  do.\\textsc{1pl.pst}  certainly it  do.\\textsc{1pl.pst}",
        "imtwordsbare": [
            "it",
            "do.1pl.pst",
            "certainly",
            "it",
            "do.1pl.pst"
        ],
        "imtwordshtml": [
            "it",
            "do.<span class=\"sc\">1pl.pst</span>",
            "certainly",
            "it",
            "do.<span class=\"sc\">1pl.pst</span>"
        ],
        "imtwordstex": [
            "it",
            "do.\\textsc{1pl.pst}",
            "certainly",
            "it",
            "do.\\textsc{1pl.pst}"
        ],
        "language": "216/chapters/09Alvanoudi.tex",
        "src": "\\textbf{To} \\textbf{\\underline{k\u00e1}name:.} sa\\underline{f\u00f3s}       to k\u00e1name",
        "srcwordsbare": [
            "To",
            "\\underline{k\u00e1name:.}",
            "sa\\underline{f\u00f3s}",
            "to",
            "k\u00e1name"
        ],
        "srcwordshtml": [
            "<span class=\"bf\">To</span>",
            "<span class=\"bf\">\\underline{k\u00e1</span>name:.}",
            "sa\\underline{f\u00f3s}",
            "to",
            "k\u00e1name"
        ],
        "srcwordstex": [
            "\\textbf{To}",
            "\\textbf{\\underline{k\u00e1}name:.}",
            "sa\\underline{f\u00f3s}",
            "to",
            "k\u00e1name"
        ],
        "trs": "We did it. We certainly did it'}\\\\",
        "wlength": 5
    },
    {
        "ID": "09Alvanoudi-358893",
        "categories": [
            "3sg",
            "neg",
            "pass",
            "prs"
        ],
        "clength": 47,
        "filename": "216/chapters/09Alvanoudi.tex",
        "imt": "no    \\textsc{neg} need.\\textsc{3sg.pass.prs} now",
        "imtwordsbare": [
            "no",
            "NEG",
            "need.3sg.pass.prs",
            "now"
        ],
        "imtwordshtml": [
            "no",
            "<span class=\"sc\">neg</span>",
            "need.<span class=\"sc\">3sg.pass.prs</span>",
            "now"
        ],
        "imtwordstex": [
            "no",
            "\\textsc{neg}",
            "need.\\textsc{3sg.pass.prs}",
            "now"
        ],
        "language": "216/chapters/09Alvanoudi.tex",
        "src": "O\u00e7i. \u00f0e >xri\u00e1zete               \\textbf{t\u03ccra:,}",
        "srcwordsbare": [
            "O\u00e7i.",
            "\u00f0e",
            ">xri\u00e1zete",
            "t\u03ccra:,"
        ],
        "srcwordshtml": [
            "O\u00e7i.",
            "\u00f0e",
            ">xri\u00e1zete",
            "<span class=\"bf\">t\u03ccra:,</span>"
        ],
        "srcwordstex": [
            "O\u00e7i.",
            "\u00f0e",
            ">xri\u00e1zete",
            "\\textbf{t\u03ccra:,}"
        ],
        "trs": "No. I don\u2019t need to switch it off now,'}\\\\",
        "wlength": 4
    },
    {
        "ID": "09Alvanoudi--39858",
        "categories": [
            "3sg",
            "pass",
            "prs"
        ],
        "clength": 59,
        "filename": "216/chapters/09Alvanoudi.tex",
        "imt": "cook.\\textsc{3sg.pass.prs} still",
        "imtwordsbare": [
            "cook.3sg.pass.prs",
            "still"
        ],
        "imtwordshtml": [
            "cook.<span class=\"sc\">3sg.pass.prs</span>",
            "still"
        ],
        "imtwordstex": [
            "cook.\\textsc{3sg.pass.prs}",
            "still"
        ],
        "language": "216/chapters/09Alvanoudi.tex",
        "src": "\\textbf{ma\u029di\\underline{r\u00e9}\u00b0vete}        \\textbf{(ak\u03ccma).}<=",
        "srcwordsbare": [
            "ma\u029di\\underline{r\u00e9\u00b0vete}",
            "(ak\u03ccma).<="
        ],
        "srcwordshtml": [
            "<span class=\"bf\">ma\u029di\\underline{r\u00e9</span>\u00b0vete}",
            "<span class=\"bf\">(ak\u03ccma).</span><="
        ],
        "srcwordstex": [
            "\\textbf{ma\u029di\\underline{r\u00e9}\u00b0vete}",
            "\\textbf{(ak\u03ccma).}<="
        ],
        "trs": "the food is still cooking.'}\\\\",
        "wlength": 2
    },
    {
        "ID": "09Alvanoudi-298677",
        "categories": [
            "3sg",
            "pass",
            "prs"
        ],
        "clength": 92,
        "filename": "216/chapters/09Alvanoudi.tex",
        "imt": "part  now   cook.\\textsc{3sg.pass.prs} still    yes",
        "imtwordsbare": [
            "part",
            "now",
            "cook.3sg.pass.prs",
            "still",
            "yes"
        ],
        "imtwordshtml": [
            "part",
            "now",
            "cook.<span class=\"sc\">3sg.pass.prs</span>",
            "still",
            "yes"
        ],
        "imtwordstex": [
            "part",
            "now",
            "cook.\\textsc{3sg.pass.prs}",
            "still",
            "yes"
        ],
        "language": "216/chapters/09Alvanoudi.tex",
        "src": "={[}\\underline{A}. >\\textbf{t\u03ccra} \\textbf{ma\u029dir\u00e9ve}{]}\\textbf{{[}te} \\textbf{ak\u03cc{]}mi.} ne.<",
        "srcwordsbare": [
            "={[}\\underline{A}.",
            ">t\u03ccra",
            "ma\u029dir\u00e9ve{]}{[te}",
            "ak\u03cc{]mi.}",
            "ne.<"
        ],
        "srcwordshtml": [
            "={[}\\underline{A}.",
            "><span class=\"bf\">t\u03ccra</span>",
            "<span class=\"bf\">ma\u029dir\u00e9ve</span>{]}<span class=\"bf\">{[</span>te}",
            "<span class=\"bf\">ak\u03cc{]</span>mi.}",
            "ne.<"
        ],
        "srcwordstex": [
            "={[}\\underline{A}.",
            ">\\textbf{t\u03ccra}",
            "\\textbf{ma\u029dir\u00e9ve}{]}\\textbf{{[}te}",
            "\\textbf{ak\u03cc{]}mi.}",
            "ne.<"
        ],
        "time": "present",
        "trs": "Ah. now it\u2019s still cooking. yes.'}\\\\",
        "wlength": 5
    },
    {
        "ID": "09Alvanoudi-132864",
        "categories": [
            "(m)",
            "1pl",
            "acc",
            "pst",
            "sbjv",
            "sg"
        ],
        "clength": 85,
        "filename": "216/chapters/09Alvanoudi.tex",
        "imt": "begin.\\textsc{1pl.pst}  \\textsc{sbjv} go.\\textsc{1pl} to Zitho\\textsc{(m).acc.sg}",
        "imtwordsbare": [
            "begin.1pl.pst",
            "SBJV",
            "go.1PL",
            "to",
            "Zitho(m).acc.sg"
        ],
        "imtwordshtml": [
            "begin.<span class=\"sc\">1pl.pst</span>",
            "<span class=\"sc\">sbjv</span>",
            "go.<span class=\"sc\">1pl</span>",
            "to",
            "Zitho<span class=\"sc\">(m).acc.sg</span>"
        ],
        "imtwordstex": [
            "begin.\\textsc{1pl.pst}",
            "\\textsc{sbjv}",
            "go.\\textsc{1pl}",
            "to",
            "Zitho\\textsc{(m).acc.sg}"
        ],
        "language": "216/chapters/09Alvanoudi.tex",
        "src": "\u00b0\\textbf{ksecin\u00edsame} \\textbf{na}    \\textbf{p\u00e1me}   sto                       Z\u00ed\u03b8o?\u00b0",
        "srcwordsbare": [
            "\u00b0ksecin\u00edsame",
            "na",
            "p\u00e1me",
            "sto",
            "Z\u00ed\u03b8o?\u00b0"
        ],
        "srcwordshtml": [
            "\u00b0<span class=\"bf\">ksecin\u00edsame</span>",
            "<span class=\"bf\">na</span>",
            "<span class=\"bf\">p\u00e1me</span>",
            "sto",
            "Z\u00ed\u03b8o?\u00b0"
        ],
        "srcwordstex": [
            "\u00b0\\textbf{ksecin\u00edsame}",
            "\\textbf{na}",
            "\\textbf{p\u00e1me}",
            "sto",
            "Z\u00ed\u03b8o?\u00b0"
        ],
        "trs": "were we going to Zithos?'}\\\\",
        "wlength": 5
    },
    {
        "ID": "09Alvanoudi--59919",
        "categories": [
            "1pl",
            "pst",
            "sbjv"
        ],
        "clength": 94,
        "filename": "216/chapters/09Alvanoudi.tex",
        "imt": "begin.\\textsc{1pl.pst}  h \\textsc{sbjv} \\textsc{sbjv} go.\\textsc{1pl} for coffee",
        "imtwordsbare": [
            "begin.1pl.pst",
            "h",
            "SBJV",
            "SBJV",
            "go.1PL",
            "for",
            "coffee"
        ],
        "imtwordshtml": [
            "begin.<span class=\"sc\">1pl.pst</span>",
            "h",
            "<span class=\"sc\">sbjv</span>",
            "<span class=\"sc\">sbjv</span>",
            "go.<span class=\"sc\">1pl</span>",
            "for",
            "coffee"
        ],
        "imtwordstex": [
            "begin.\\textsc{1pl.pst}",
            "h",
            "\\textsc{sbjv}",
            "\\textsc{sbjv}",
            "go.\\textsc{1pl}",
            "for",
            "coffee"
        ],
        "language": "216/chapters/09Alvanoudi.tex",
        "src": "\\textbf{ksecin\u00edsame}, h \\textbf{na-}   \\textbf{na} \\textbf{p\u00e1me}  \\textbf{\u029da}   \\textbf{kaf\u00e9.}",
        "srcwordsbare": [
            "ksecin\u00edsame,",
            "h",
            "na-",
            "na",
            "p\u00e1me",
            "\u029da",
            "kaf\u00e9."
        ],
        "srcwordshtml": [
            "<span class=\"bf\">ksecin\u00edsame</span>,",
            "h",
            "<span class=\"bf\">na-</span>",
            "<span class=\"bf\">na</span>",
            "<span class=\"bf\">p\u00e1me</span>",
            "<span class=\"bf\">\u029da</span>",
            "<span class=\"bf\">kaf\u00e9.</span>"
        ],
        "srcwordstex": [
            "\\textbf{ksecin\u00edsame},",
            "h",
            "\\textbf{na-}",
            "\\textbf{na}",
            "\\textbf{p\u00e1me}",
            "\\textbf{\u029da}",
            "\\textbf{kaf\u00e9.}"
        ],
        "trs": "were we going for coffee.'}\\\\",
        "wlength": 7
    }
]